frozenintset/__init__.py
frozenintset/_impl.py
frozenintset/py.typed
frozenintset-0.1.3.dist-info/METADATA
frozenintset-0.1.3.dist-info/WHEEL
frozenintset-0.1.3.dist-info/licenses/LICENSE
frozenintset-0.1.3.dist-info/RECORD
