Metadata-Version: 2.4
Name: frozenintset
Version: 0.1.3
Summary: An immutable, memory-efficient set of integers.
Project-URL: Source, https://github.com/scravy/frozenintset
Project-URL: Tracker, https://github.com/scravy/frozenintset/issues
Author-email: Julian Bertram <tirednesscankill@warhog.net>
License: MIT
License-File: LICENSE
Keywords: compressed,immutable,integers,range,set
Classifier: Development Status :: 4 - Beta
Classifier: Intended Audience :: Developers
Classifier: License :: OSI Approved :: MIT License
Classifier: Operating System :: OS Independent
Classifier: Programming Language :: Python :: 3
Classifier: Programming Language :: Python :: 3.11
Classifier: Programming Language :: Python :: 3.12
Classifier: Programming Language :: Python :: 3.13
Classifier: Topic :: Software Development :: Libraries
Requires-Python: >=3.11
